test.py
atlib/AIR780EU.py
atlib/AT_Device.py
atlib/GSM_Device.py
atlib/LTE_Device.py
atlib/Operator.py
atlib/SIM7070X.py
atlib/SIM7600GH.py
atlib/SMS_Group.py
atlib/Status.py
atlib/__init__.py
atlib/helpers.py
atlib/named_tuples.py
atlib/setup_logger.py
atlib-0.5.2.dist-info/licenses/LICENSE
atlib-0.5.2.dist-info/METADATA
atlib-0.5.2.dist-info/WHEEL
atlib-0.5.2.dist-info/top_level.txt
atlib-0.5.2.dist-info/RECORD
