Metadata-Version: 2.4
Name: atlib
Version: 0.5.2
Summary: A library to interact with serial AT devices
Author-email: "Chris L." <stylesuxx@gmail.com>, Timothy van der Valk <no-reply@example.com>
License: MIT License
Project-URL: Homepage, https://github.com/stylesuxx/atlib
Project-URL: Issues, https://github.com/stylesuxx/atlib/issues
Classifier: Programming Language :: Python :: 3
Classifier: Operating System :: OS Independent
Requires-Python: >=3.8
License-File: LICENSE
Requires-Dist: pyserial
Dynamic: license-file
